setup.py
AllWhatsPy/__init__.py
allwhatspy.egg-info/PKG-INFO
allwhatspy.egg-info/SOURCES.txt
allwhatspy.egg-info/dependency_links.txt
allwhatspy.egg-info/requires.txt
allwhatspy.egg-info/top_level.txt