Metadata-Version: 2.1
Name: allwhatspy
Version: 0.2.0.6
Summary: Descontinuado. Utilize pip install -U allwhatspy-awp
Author: Lucas Lourenço
Author-email: dev.lucaslourenco@gmail.com
License: MIT License
Keywords: descontinuado
